semilearn/__init__.py
semilearn/algorithms/__init__.py
semilearn/algorithms/adamatch/__init__.py
semilearn/algorithms/adamatch/adamatch.py
semilearn/algorithms/adamatch/utils.py
semilearn/algorithms/comatch/__init__.py
semilearn/algorithms/comatch/comatch.py
semilearn/algorithms/crmatch/__init__.py
semilearn/algorithms/crmatch/crmatch.py
semilearn/algorithms/dash/__init__.py
semilearn/algorithms/dash/dash.py
semilearn/algorithms/dash/utils.py
semilearn/algorithms/defixmatch/__init__.py
semilearn/algorithms/defixmatch/defixmatch.py
semilearn/algorithms/fixmatch/__init__.py
semilearn/algorithms/fixmatch/fixmatch.py
semilearn/algorithms/flexmatch/__init__.py
semilearn/algorithms/flexmatch/flexmatch.py
semilearn/algorithms/flexmatch/utils.py
semilearn/algorithms/freematch/__init__.py
semilearn/algorithms/freematch/freematch.py
semilearn/algorithms/freematch/utils.py
semilearn/algorithms/fullysupervised/__init__.py
semilearn/algorithms/fullysupervised/fullysupervised.py
semilearn/algorithms/hooks/__init__.py
semilearn/algorithms/hooks/dist_align.py
semilearn/algorithms/hooks/masking.py
semilearn/algorithms/hooks/pseudo_label.py
semilearn/algorithms/meanteacher/__init__.py
semilearn/algorithms/meanteacher/meanteacher.py
semilearn/algorithms/mixmatch/__init__.py
semilearn/algorithms/mixmatch/mixmatch.py
semilearn/algorithms/pimodel/__init__.py
semilearn/algorithms/pimodel/pimodel.py
semilearn/algorithms/pseudolabel/__init__.py
semilearn/algorithms/pseudolabel/pseudolabel.py
semilearn/algorithms/remixmatch/__init__.py
semilearn/algorithms/remixmatch/remixmatch.py
semilearn/algorithms/simmatch/__init__.py
semilearn/algorithms/simmatch/simmatch.py
semilearn/algorithms/softmatch/__init__.py
semilearn/algorithms/softmatch/softmatch.py
semilearn/algorithms/softmatch/utils.py
semilearn/algorithms/uda/__init__.py
semilearn/algorithms/uda/uda.py
semilearn/algorithms/utils/__init__.py
semilearn/algorithms/utils/misc.py
semilearn/algorithms/utils/ops.py
semilearn-0.3.2.dist-info/LICENSE.txt
semilearn-0.3.2.dist-info/METADATA
semilearn-0.3.2.dist-info/WHEEL
semilearn-0.3.2.dist-info/top_level.txt
semilearn-0.3.2.dist-info/RECORD
