Metadata-Version: 2.1
Name: semilearn
Version: 0.3.2
Summary: Unfied Semi-Supervised Learning Benchmark
Home-page: https://github.com/microsoft/Semi-supervised-learning
Author: Yidong Wang*, Hao Chen*, Yue Fan*, Wang Sun, Ran Tao, Wenxin Hou, Renjie Wang, Heli Qi, Zhen Wu,Satoshi Nakamura, Wei Ye, Marios Savvides, Bhiksha Raj, Takahiro Shinozaki, Bernt Schiele, Jindong Wang, Xing Xie, Yue Zhang
Author-email: yidongwang37@gmail.com, haoc3@andrew.cmu.edu, yuefan@mpi-inf.mpg.de, jindwang@microsoft.com
Keywords: pytorch semi-supervised-learning
Requires-Python: >=3.9
License-File: LICENSE.txt
Requires-Dist: matplotlib (>=3.5.2)
Requires-Dist: numpy (>=1.24.4)
Requires-Dist: Pillow (>=9.0.0)
Requires-Dist: progress (>=1.6)
Requires-Dist: ruamel.yaml (>=0.17.21)
Requires-Dist: ruamel.yaml.clib (>=0.2.6)
Requires-Dist: scikit-image (>=0.19.3)
Requires-Dist: scikit-learn (>=1.0.2)
Requires-Dist: scipy (>=1.10.0)
Requires-Dist: tensorboard (>=2.9.1)
Requires-Dist: timm (>=0.5.4)
Requires-Dist: torch (>=1.12.0)
Requires-Dist: torchaudio (>=0.12.0)
Requires-Dist: torchvision (>=0.13.0)
Requires-Dist: tqdm (>=4.64.0)
Requires-Dist: transformers (>=4.30.0)
Requires-Dist: wandb
Requires-Dist: aim
